{"address_obj": {"street1": "Apollolaan 2", "street2": "", "city": "Amsterdam", "state": "North Holland Province", "country": "The Netherlands", "postalcode": "1077 BA", "address_string": "Apollolaan 2, 1077 BA Amsterdam The Netherlands"}, "latitude": "52.34859", "rating": "4.0", "location_id": "1740219", "trip_types": [{"name": "business", "value": "553", "localized_name": "Business"}, {"name": "couples", "value": "799", "localized_name": "Couples"}, {"name": "solo", "value": "101", "localized_name": "Solo travel"}, {"name": "family", "value": "236", "localized_name": "Family"}, {"name": "friends", "value": "302", "localized_name": "Friends getaway"}], "reviews": [{"id": "722319542", "lang": "en", "location_id": "1740219", "published_date": "2019-10-29T08:04:03-0400", "rating": 5, "helpful_votes": "0", "rating_image_url": "http://www.tripadvisor.com/img/cdsi/img2/ratings/traveler/s5.0-21516-5.svg", "url": "https://www.tripadvisor.com/ShowUserReviews-g188590-d1740219-r722319542-Apollo_Hotel_Amsterdam_a_Tribute_Portfolio_Hotel-Amsterdam_North_Holland_Provinc.html?m=21516#review722319542", "trip_type": null, "travel_date": "2019-10", "text": "Our 6-day stay at the Apollo was excellent, the only drawback being its distance from the center of the city. We had about a 10 minute walk to the tram, not bad at all, though it was cold and rainy...", "user": {"username": "barbararC7463HJ", "user_location": {"name": null, "id": null}}, "title": "Excellent Hotel & Service, a Bit Away from Center of City"}, {"id": "719415286", "lang": "en", "location_id": "1740219", "published_date": "2019-10-18T08:38:47-0400", "rating": 1, "helpful_votes": "0", "rating_image_url": "http://www.tripadvisor.com/img/cdsi/img2/ratings/traveler/s1.0-21516-5.svg", "url": "https://www.tripadvisor.com/ShowUserReviews-g188590-d1740219-r719415286-Apollo_Hotel_Amsterdam_a_Tribute_Portfolio_Hotel-Amsterdam_North_Holland_Provinc.html?m=21516#review719415286", "trip_type": "Business", "travel_date": "2019-10", "text": "It is tragic to arrive at a hotel at night in the rain to find there is no room available because they have double booked! Not just me but other guests as well.\nBookings are electronic and they know...", "user": {"username": "CHews", "user_location": {"name": "Chelmsford, United Kingdom", "id": "503775"}}, "title": "Double booked !"}, {"id": "717731595", "lang": "en", "location_id": "1740219", "published_date": "2019-10-12T12:14:18-0400", "rating": 1, "helpful_votes": "0", "rating_image_url": "http://www.tripadvisor.com/img/cdsi/img2/ratings/traveler/s1.0-21516-5.svg", "url": "https://www.tripadvisor.com/ShowUserReviews-g188590-d1740219-r717731595-Apollo_Hotel_Amsterdam_a_Tribute_Portfolio_Hotel-Amsterdam_North_Holland_Provinc.html?m=21516#review717731595", "trip_type": null, "travel_date": "2019-10", "text": "We knew this hotel was not in the high demand tourist are of Amsterdam and that and the price of the room was drew us to it. We tend to prefer to stay out of the tourist areas but near the transit...", "user": {"username": "Chrisinkingwood2", "user_location": {"name": "Houston, Texas", "id": "56003"}}, "title": "Possibly the worst Marriott property we have ever visited!"}, {"id": "717093196", "lang": "en", "location_id": "1740219", "published_date": "2019-10-10T11:04:33-0400", "rating": 3, "helpful_votes": "0", "rating_image_url": "http://www.tripadvisor.com/img/cdsi/img2/ratings/traveler/s3.0-21516-5.svg", "url": "https://www.tripadvisor.com/ShowUserReviews-g188590-d1740219-r717093196-Apollo_Hotel_Amsterdam_a_Tribute_Portfolio_Hotel-Amsterdam_North_Holland_Provinc.html?m=21516#review717093196", "trip_type": "Business", "travel_date": "2019-09", "text": "I wanted to love this hotel, but I just...didn't.  I'm a Platinum member and usually like Tributes, but this one wasn't up to snuff.  Rooms were much smaller than other AMS hotels (even with the...", "user": {"username": "kkbirds", "user_location": {"name": "London, United Kingdom", "id": "186338"}}, "title": "Great on some things; meh on others"}, {"id": "715780934", "lang": "en", "location_id": "1740219", "published_date": "2019-10-06T08:51:14-0400", "rating": 5, "helpful_votes": "0", "rating_image_url": "http://www.tripadvisor.com/img/cdsi/img2/ratings/traveler/s5.0-21516-5.svg", "url": "https://www.tripadvisor.com/ShowUserReviews-g188590-d1740219-r715780934-Apollo_Hotel_Amsterdam_a_Tribute_Portfolio_Hotel-Amsterdam_North_Holland_Provinc.html?m=21516#review715780934", "trip_type": "Business", "travel_date": "2019-10", "text": "It's been a while since I last stayed at a Marriott hotel, and I was pleasantly surprised by the quality of the hotel and the services. The hotel is stylishly decorated from lobby to the rooms...", "user": {"username": "HayleyZhu", "user_location": {"name": "Hong Kong, China", "id": "294217"}}, "title": "Awesome hotel in a quiet but trendy area"}], "write_review": "https://www.tripadvisor.com/UserReview-g188590-d1740219-m21516-Apollo_Hotel_Amsterdam_a_Tribute_Portfolio_Hotel-Amsterdam_North_Holland_Province.html", "ancestors": [{"abbrv": null, "level": "City", "name": "Amsterdam", "location_id": "188590"}, {"abbrv": null, "level": "Province", "name": "North Holland Province", "location_id": "188587"}, {"abbrv": null, "level": "Country", "name": "The Netherlands", "location_id": "188553"}], "longitude": "4.885211", "hours": null, "percent_recommended": 69, "review_rating_count": {"1": "79", "2": "112", "3": "345", "4": "807", "5": "802"}, "subratings": [{"rating_image_url": "https://static.tacdn.com/img2/ratings/traveler/ss4.0.gif", "name": "rate_location", "value": "4.0", "localized_name": "Location"}, {"rating_image_url": "https://static.tacdn.com/img2/ratings/traveler/ss4.0.gif", "name": "rate_sleep", "value": "4.0", "localized_name": "Sleep Quality"}, {"rating_image_url": "https://static.tacdn.com/img2/ratings/traveler/ss4.0.gif", "name": "rate_room", "value": "4.0", "localized_name": "Rooms"}, {"rating_image_url": "https://static.tacdn.com/img2/ratings/traveler/ss4.0.gif", "name": "rate_service", "value": "4.0", "localized_name": "Service"}, {"rating_image_url": "https://static.tacdn.com/img2/ratings/traveler/ss4.0.gif", "name": "rate_value", "value": "4.0", "localized_name": "Value"}, {"rating_image_url": "https://static.tacdn.com/img2/ratings/traveler/ss4.0.gif", "name": "rate_cleanliness", "value": "4.0", "localized_name": "Cleanliness"}], "ranking_data": {"ranking_string": "#150 of 400 hotels in Amsterdam", "ranking_out_of": "400", "geo_location_id": "188590", "ranking": "150", "geo_location_name": "Amsterdam", "ranking_string_detail": null}, "photo_count": "895", "location_string": "Amsterdam, North Holland Province", "web_url": "https://www.tripadvisor.com/Hotel_Review-g188590-d1740219-Reviews-Apollo_Hotel_Amsterdam_a_Tribute_Portfolio_Hotel-Amsterdam_North_Holland_Province.html?m=21516", "price_level": "$$$", "rating_image_url": "http://www.tripadvisor.com/img/cdsi/img2/ratings/traveler/4.0-21516-5.svg", "awards": [{"award_type": "Certificate of Excellence", "year": "2019", "images": {"small": "http://www.tripadvisor.com/img/cdsi/img2/awards/CERTIFICATE_OF_EXCELLENCE_v2_small-21516-5.jpg", "large": "http://www.tripadvisor.com/img/cdsi/img2/awards/CERTIFICATE_OF_EXCELLENCE_2019_en_US_large-21516-5.jpg"}, "categories": [], "display_name": "Certificate of Excellence 2019"}], "name": "Apollo Hotel Amsterdam, a Tribute Portfolio Hotel", "num_reviews": "2145", "category": {"name": "hotel", "localized_name": "Hotel"}, "subcategory": [{"name": "hotel", "localized_name": "Hotel"}], "see_all_photos": "https://www.tripadvisor.com/Hotel_Review-g188590-d1740219-m21516-Reviews-Apollo_Hotel_Amsterdam_a_Tribute_Portfolio_Hotel-Amsterdam_North_Holland_Province.html#photos"}