{"address_obj": {"street1": "Carretera Provincial Barranco Monyo 55", "street2": "Las Rotas", "city": "Denia", "state": "Province of Alicante", "country": "Spain", "postalcode": "03700", "address_string": "Carretera Provincial Barranco Monyo 55 Las Rotas, 03700, Denia Spain"}, "latitude": "38.82709", "rating": "3.0", "location_id": "1832302", "trip_types": [{"name": "business", "value": "1", "localized_name": "Business"}, {"name": "couples", "value": "13", "localized_name": "Couples"}, {"name": "solo", "value": "0", "localized_name": "Solo travel"}, {"name": "family", "value": "3", "localized_name": "Family"}, {"name": "friends", "value": "2", "localized_name": "Friends getaway"}], "reviews": [{"id": "250694400", "lang": "en", "location_id": "1832302", "published_date": "2015-01-23T13:10:54-0500", "rating": 4, "helpful_votes": "0", "rating_image_url": "http://www.tripadvisor.com/img/cdsi/img2/ratings/traveler/s4.0-21516-5.svg", "url": "https://www.tripadvisor.com/ShowUserReviews-g609043-d1832302-r250694400-Hotel_Montgo-Denia_Costa_Blanca_Province_of_Alicante_Valencian_Country.html?m=21516#review250694400", "trip_type": "Friends getaway", "travel_date": "2014-12", "text": "We stayed for 6 nights - a quick 5 minute drive from Denia town centre, the staff was friendly and helpful, the room was clean, and the free wifi worked.  The room was small, but fine since we only...", "user": {"username": "M J", "user_location": {"name": "Calgary, Canada", "id": "154913"}}, "title": "Clean, quiet and efficient - good spot if you basically need a place to sleep"}, {"id": "250662691", "lang": "en", "location_id": "1832302", "published_date": "2015-01-23T08:43:26-0500", "rating": 4, "helpful_votes": "0", "rating_image_url": "http://www.tripadvisor.com/img/cdsi/img2/ratings/traveler/s4.0-21516-5.svg", "url": "https://www.tripadvisor.com/ShowUserReviews-g609043-d1832302-r250662691-Hotel_Montgo-Denia_Costa_Blanca_Province_of_Alicante_Valencian_Country.html?m=21516#review250662691", "trip_type": "Business", "travel_date": "2015-01", "text": "Was looking for a cheap place to spend a night in Denis upon a late arrival and early depart and this turned to be as described by follow visitors.. Quiet, clean and economic.. Breakfast was included...", "user": {"username": "Herman L", "user_location": {"name": "Gibraltar", "id": "187510"}}, "title": "Exactly was it says on the tin"}, {"id": "80361858", "lang": "en", "location_id": "1832302", "published_date": "2010-09-20T14:27:59-0400", "rating": 4, "helpful_votes": "1", "rating_image_url": "http://www.tripadvisor.com/img/cdsi/img2/ratings/traveler/s4.0-21516-5.svg", "url": "https://www.tripadvisor.com/ShowUserReviews-g609043-d1832302-r80361858-Hotel_Montgo-Denia_Costa_Blanca_Province_of_Alicante_Valencian_Country.html?m=21516#review80361858", "trip_type": "Couples", "travel_date": "2010-09", "text": "We booked this hotel for just one night. We had ferry to catch in Denia early morning so we really did not need expensive hotel near beach. This one looks like a recent one. Trendy, modern, well...", "user": {"username": "iberia_travel", "user_location": {"name": "Lisboa", "id": null}}, "title": "It's true that it was for one night, but no windows?!..."}, {"id": "476412138", "lang": "es", "location_id": "1832302", "published_date": "2017-04-17T05:48:34-0400", "rating": 2, "helpful_votes": "0", "rating_image_url": "http://www.tripadvisor.com/img/cdsi/img2/ratings/traveler/s2.0-21516-5.svg", "url": "https://www.tripadvisor.com/ShowUserReviews-g609043-d1832302-r476412138-Hotel_Montgo-Denia_Costa_Blanca_Province_of_Alicante_Valencian_Country.html?m=21516#review476412138", "trip_type": "Couples", "travel_date": "2017-04", "text": "El hotel es barato pero no merece m\u00e1s. La limpieza de la habitaci\u00f3n regular, la habitaci\u00f3n diminuta, la amabilidad del personal justita y el restaurante bastante malo. Lo \u00fanico bueno es que es un...", "user": {"username": "rachelmctm", "user_location": {"name": "Valencia, Spain", "id": "187529"}}, "title": "Regular"}, {"id": "410880941", "lang": "es", "location_id": "1832302", "published_date": "2016-08-26T00:22:14-0400", "rating": 1, "helpful_votes": "4", "rating_image_url": "http://www.tripadvisor.com/img/cdsi/img2/ratings/traveler/s1.0-21516-5.svg", "url": "https://www.tripadvisor.com/ShowUserReviews-g609043-d1832302-r410880941-Hotel_Montgo-Denia_Costa_Blanca_Province_of_Alicante_Valencian_Country.html?m=21516#review410880941", "trip_type": "Friends getaway", "travel_date": "2016-08", "text": "Aunque la ubicaci\u00f3n est\u00e1 ok y las instalaciones en cuanto a tama\u00f1o/decoraci\u00f3n son correctas la limpieza brilla por su ausencia, detalles como q dejemos las toallas en suelo de ducha para que sean...", "user": {"username": "ccasber", "user_location": {"name": "Madrid, Spain", "id": "187514"}}, "title": "No recomendable en absoluto"}], "write_review": "https://www.tripadvisor.com/UserReview-g609043-d1832302-m21516-Hotel_Montgo-Denia_Costa_Blanca_Province_of_Alicante_Valencian_Country.html", "ancestors": [{"abbrv": null, "level": "Municipality", "name": "Denia", "location_id": "609043"}, {"abbrv": null, "level": "Province", "name": "Costa Blanca", "location_id": "187523"}, {"abbrv": null, "level": "Province", "name": "Province of Alicante", "location_id": "187524"}, {"abbrv": null, "level": "Region", "name": "Valencian Country", "location_id": "187521"}, {"abbrv": null, "level": "Country", "name": "Spain", "location_id": "187427"}], "longitude": "0.14392", "hours": null, "percent_recommended": 66, "review_rating_count": {"1": "3", "2": "5", "3": "6", "4": "3", "5": "3"}, "subratings": [{"rating_image_url": "https://static.tacdn.com/img2/ratings/traveler/ss4.0.gif", "name": "rate_sleep", "value": "4.0", "localized_name": "Sleep Quality"}, {"rating_image_url": "https://static.tacdn.com/img2/ratings/traveler/ss3.5.gif", "name": "rate_location", "value": "3.5", "localized_name": "Location"}, {"rating_image_url": "https://static.tacdn.com/img2/ratings/traveler/ss3.0.gif", "name": "rate_room", "value": "3.0", "localized_name": "Rooms"}, {"rating_image_url": "https://static.tacdn.com/img2/ratings/traveler/ss4.0.gif", "name": "rate_service", "value": "4.0", "localized_name": "Service"}, {"rating_image_url": "https://static.tacdn.com/img2/ratings/traveler/ss2.5.gif", "name": "rate_value", "value": "2.5", "localized_name": "Value"}, {"rating_image_url": "https://static.tacdn.com/img2/ratings/traveler/ss4.0.gif", "name": "rate_cleanliness", "value": "4.0", "localized_name": "Cleanliness"}], "ranking_data": {"ranking_string": "#6 of 11 B&Bs / Inns in Denia", "ranking_out_of": "11", "geo_location_id": "609043", "ranking": "6", "geo_location_name": "Denia", "ranking_string_detail": null}, "photo_count": "8", "location_string": "Denia, Costa Blanca, Province of Alicante, Valencian Country", "web_url": "https://www.tripadvisor.com/Hotel_Review-g609043-d1832302-Reviews-Hotel_Montgo-Denia_Costa_Blanca_Province_of_Alicante_Valencian_Country.html?m=21516", "price_level": "$", "rating_image_url": "http://www.tripadvisor.com/img/cdsi/img2/ratings/traveler/3.0-21516-5.svg", "awards": [], "name": "Hotel Montgo", "num_reviews": "20", "category": {"name": "hotel", "localized_name": "Hotel"}, "subcategory": [{"name": "bb", "localized_name": "Bed and Breakfast"}], "see_all_photos": "https://www.tripadvisor.com/Hotel_Review-g609043-d1832302-m21516-Reviews-Hotel_Montgo-Denia_Costa_Blanca_Province_of_Alicante_Valencian_Country.html#photos"}