{"address_obj": {"street1": "Plaza de Espana", "street2": "", "city": "Nerja", "state": "Province of Malaga", "country": "Spain", "postalcode": "29780", "address_string": "Plaza de Espana, 29780 Nerja Spain"}, "latitude": "36.745926", "rating": "4.5", "location_id": "1858091", "trip_types": [{"name": "business", "value": "3", "localized_name": "Business"}, {"name": "couples", "value": "284", "localized_name": "Couples"}, {"name": "solo", "value": "16", "localized_name": "Solo travel"}, {"name": "family", "value": "62", "localized_name": "Family"}, {"name": "friends", "value": "56", "localized_name": "Friends getaway"}], "reviews": [{"id": "716333435", "lang": "en", "location_id": "1858091", "published_date": "2019-10-08T07:30:09-0400", "rating": 5, "helpful_votes": "0", "rating_image_url": "http://www.tripadvisor.com/img/cdsi/img2/ratings/traveler/s5.0-21516-5.svg", "url": "https://www.tripadvisor.com/ShowUserReviews-g315917-d1858091-r716333435-Hotel_Mena_Plaza-Nerja_Costa_del_Sol_Province_of_Malaga_Andalucia.html?m=21516#review716333435", "trip_type": "Friends getaway", "travel_date": "2019-10", "text": "Have now been back to this hotel three times and each time I am totally impressed with its cleanliness and excellent staff. Booked a room with a balcony which is well worth the extra \u20ac8 per night...", "user": {"username": "ShazWSM", "user_location": {"name": "Lympsham, United Kingdom", "id": "2702597"}}, "title": "Excellent hotel and staff!!"}, {"id": "710872251", "lang": "en", "location_id": "1858091", "published_date": "2019-09-18T07:51:35-0400", "rating": 5, "helpful_votes": "1", "rating_image_url": "http://www.tripadvisor.com/img/cdsi/img2/ratings/traveler/s5.0-21516-5.svg", "url": "https://www.tripadvisor.com/ShowUserReviews-g315917-d1858091-r710872251-Hotel_Mena_Plaza-Nerja_Costa_del_Sol_Province_of_Malaga_Andalucia.html?m=21516#review710872251", "trip_type": null, "travel_date": "2019-09", "text": "On arrival at 11.30 pm we were made to feel really welcome by the staff on the hotel reception desk and this continued throughout our stay. The rooms were excellent spotlessly clean and well...", "user": {"username": "tabamba", "user_location": {"name": "Troon, United Kingdom", "id": "551834"}}, "title": "Holiday with friends"}, {"id": "700516846", "lang": "en", "location_id": "1858091", "published_date": "2019-08-18T21:27:19-0400", "rating": 5, "helpful_votes": "0", "rating_image_url": "http://www.tripadvisor.com/img/cdsi/img2/ratings/traveler/s5.0-21516-5.svg", "url": "https://www.tripadvisor.com/ShowUserReviews-g315917-d1858091-r700516846-Hotel_Mena_Plaza-Nerja_Costa_del_Sol_Province_of_Malaga_Andalucia.html?m=21516#review700516846", "trip_type": "Couples", "travel_date": "2019-08", "text": "This is my second visit to this hotel and again I wasn\u2019t disappointed. How this little hotel is 2 star I will never know, I\u2019ve stayed in 4 star hotels that haven\u2019t nearly been as good as this one. It...", "user": {"username": "AEsommerville", "user_location": {"name": "Irvine, United Kingdom", "id": "186560"}}, "title": "Fabulous wee gem of a hotel"}, {"id": "692534504", "lang": "en", "location_id": "1858091", "published_date": "2019-07-25T01:32:00-0400", "rating": 4, "helpful_votes": "0", "rating_image_url": "http://www.tripadvisor.com/img/cdsi/img2/ratings/traveler/s4.0-21516-5.svg", "url": "https://www.tripadvisor.com/ShowUserReviews-g315917-d1858091-r692534504-Hotel_Mena_Plaza-Nerja_Costa_del_Sol_Province_of_Malaga_Andalucia.html?m=21516#review692534504", "trip_type": "Couples", "travel_date": "2019-06", "text": "Great location by the Balcon de Europa, great clean and modern rooms. Pool on roof top with bar was excellent and the bar staff nothing was too much, great service and great food service to the...", "user": {"username": "Mrb999trim", "user_location": {"name": "Llanelli, United Kingdom", "id": "776264"}}, "title": "Lovely find! "}, {"id": "686466378", "lang": "en", "location_id": "1858091", "published_date": "2019-07-03T07:48:17-0400", "rating": 5, "helpful_votes": "0", "rating_image_url": "http://www.tripadvisor.com/img/cdsi/img2/ratings/traveler/s5.0-21516-5.svg", "url": "https://www.tripadvisor.com/ShowUserReviews-g315917-d1858091-r686466378-Hotel_Mena_Plaza-Nerja_Costa_del_Sol_Province_of_Malaga_Andalucia.html?m=21516#review686466378", "trip_type": null, "travel_date": "2019-06", "text": "We were recommended to this place by friends who have stayed here many times. In my opinion it is highly under rated. Everything about it was great. It is spotless with very pleasant staff and is in...", "user": {"username": "Ray M", "user_location": {"name": "Dundee, United Kingdom", "id": "186518"}}, "title": "Little Gem"}], "write_review": "https://www.tripadvisor.com/UserReview-g315917-d1858091-m21516-Hotel_Mena_Plaza-Nerja_Costa_del_Sol_Province_of_Malaga_Andalucia.html", "ancestors": [{"abbrv": null, "level": "City", "name": "Nerja", "location_id": "315917"}, {"abbrv": null, "level": "Region", "name": "Costa del Sol", "location_id": "187435"}, {"abbrv": null, "level": "Province", "name": "Province of Malaga", "location_id": "2361615"}, {"abbrv": null, "level": "Region", "name": "Andalucia", "location_id": "187428"}, {"abbrv": null, "level": "Country", "name": "Spain", "location_id": "187427"}], "longitude": "-3.877351", "hours": null, "percent_recommended": 90, "review_rating_count": {"1": "12", "2": "12", "3": "36", "4": "159", "5": "244"}, "subratings": [{"rating_image_url": "https://static.tacdn.com/img2/ratings/traveler/ss5.0.gif", "name": "rate_location", "value": "5.0", "localized_name": "Location"}, {"rating_image_url": "https://static.tacdn.com/img2/ratings/traveler/ss4.0.gif", "name": "rate_sleep", "value": "4.0", "localized_name": "Sleep Quality"}, {"rating_image_url": "https://static.tacdn.com/img2/ratings/traveler/ss4.5.gif", "name": "rate_room", "value": "4.5", "localized_name": "Rooms"}, {"rating_image_url": "https://static.tacdn.com/img2/ratings/traveler/ss4.5.gif", "name": "rate_service", "value": "4.5", "localized_name": "Service"}, {"rating_image_url": "https://static.tacdn.com/img2/ratings/traveler/ss4.5.gif", "name": "rate_value", "value": "4.5", "localized_name": "Value"}, {"rating_image_url": "https://static.tacdn.com/img2/ratings/traveler/ss4.5.gif", "name": "rate_cleanliness", "value": "4.5", "localized_name": "Cleanliness"}], "ranking_data": {"ranking_string": "#13 of 40 hotels in Nerja", "ranking_out_of": "40", "geo_location_id": "315917", "ranking": "13", "geo_location_name": "Nerja", "ranking_string_detail": null}, "photo_count": "230", "location_string": "Nerja, Costa del Sol, Province of Malaga, Andalucia", "web_url": "https://www.tripadvisor.com/Hotel_Review-g315917-d1858091-Reviews-Hotel_Mena_Plaza-Nerja_Costa_del_Sol_Province_of_Malaga_Andalucia.html?m=21516", "price_level": "$", "rating_image_url": "http://www.tripadvisor.com/img/cdsi/img2/ratings/traveler/4.5-21516-5.svg", "awards": [], "name": "Hotel Mena Plaza", "num_reviews": "463", "category": {"name": "hotel", "localized_name": "Hotel"}, "subcategory": [{"name": "hotel", "localized_name": "Hotel"}], "see_all_photos": "https://www.tripadvisor.com/Hotel_Review-g315917-d1858091-m21516-Reviews-Hotel_Mena_Plaza-Nerja_Costa_del_Sol_Province_of_Malaga_Andalucia.html#photos"}