{"address_obj": {"street1": "Viriotgasse 5", "street2": "", "city": "Vienna", "state": null, "country": "Austria", "postalcode": "1090", "address_string": "Viriotgasse 5, Vienna 1090 Austria"}, "latitude": "48.23072", "rating": "4.0", "location_id": "230932", "trip_types": [{"name": "business", "value": "30", "localized_name": "Business"}, {"name": "couples", "value": "39", "localized_name": "Couples"}, {"name": "solo", "value": "12", "localized_name": "Solo travel"}, {"name": "family", "value": "26", "localized_name": "Family"}, {"name": "friends", "value": "13", "localized_name": "Friends getaway"}], "reviews": [{"id": "719233545", "lang": "en", "location_id": "230932", "published_date": "2019-10-17T18:19:59-0400", "rating": 4, "helpful_votes": "0", "rating_image_url": "http://www.tripadvisor.com/img/cdsi/img2/ratings/traveler/s4.0-21516-5.svg", "url": "https://www.tripadvisor.com/ShowUserReviews-g190454-d230932-r719233545-Arthotel_ANA_Gala_Vienna-Vienna.html?m=21516#review719233545", "trip_type": null, "travel_date": "2019-10", "text": "Was a nice hotel and a good place to stay.  It is very close to Nussdorfer Strasse on Line U6 and the recommended stop to use to access the hotel.  The room was comfortable, the bed and pillow were...", "user": {"username": "ELHV", "user_location": {"name": "Toronto, Canada", "id": "155019"}}, "title": "Good Choice"}, {"id": "696723814", "lang": "en", "location_id": "230932", "published_date": "2019-08-07T14:02:27-0400", "rating": 5, "helpful_votes": "0", "rating_image_url": "http://www.tripadvisor.com/img/cdsi/img2/ratings/traveler/s5.0-21516-5.svg", "url": "https://www.tripadvisor.com/ShowUserReviews-g190454-d230932-r696723814-Arthotel_ANA_Gala_Vienna-Vienna.html?m=21516#review696723814", "trip_type": "Couples", "travel_date": "2019-08", "text": "One of the best hotels . Near the metro station .very helpful stuff. Clean and hudge room. Near the hotel we have 2 supermarkets and 2 pharmacies and the famous Bipa was a walking distance from the...", "user": {"username": "196farahm", "user_location": {"name": "Cairo, Egypt", "id": "294201"}}, "title": "The best"}, {"id": "695671329", "lang": "en", "location_id": "230932", "published_date": "2019-08-05T01:30:09-0400", "rating": 4, "helpful_votes": "0", "rating_image_url": "http://www.tripadvisor.com/img/cdsi/img2/ratings/traveler/s4.0-21516-5.svg", "url": "https://www.tripadvisor.com/ShowUserReviews-g190454-d230932-r695671329-Arthotel_ANA_Gala_Vienna-Vienna.html?m=21516#review695671329", "trip_type": "Family", "travel_date": "2019-08", "text": "nice hotel. very clean  spacious rooms. the lady who works as a frontline staff( sorry i cant remember her name) very helpful.the hotel is close to tram station. close by two supermarkets and few...", "user": {"username": "pancho123", "user_location": {"name": null, "id": null}}, "title": "nice hotel"}, {"id": "683365743", "lang": "en", "location_id": "230932", "published_date": "2019-06-22T01:17:15-0400", "rating": 4, "helpful_votes": "0", "rating_image_url": "http://www.tripadvisor.com/img/cdsi/img2/ratings/traveler/s4.0-21516-5.svg", "url": "https://www.tripadvisor.com/ShowUserReviews-g190454-d230932-r683365743-Arthotel_ANA_Gala_Vienna-Vienna.html?m=21516#review683365743", "trip_type": "Family", "travel_date": "2019-06", "text": "We spent 4 days in Arthotel Ana Gala and everything was in line with expectation. Hotel is nice, rooms clean with enough space, personnel very polite and always at service. Internet was ok too. Hotel...", "user": {"username": "634ivand", "user_location": {"name": "Nis, Serbia", "id": "295382"}}, "title": "Nice Hotel"}, {"id": "680815321", "lang": "en", "location_id": "230932", "published_date": "2019-06-11T11:36:26-0400", "rating": 4, "helpful_votes": "0", "rating_image_url": "http://www.tripadvisor.com/img/cdsi/img2/ratings/traveler/s4.0-21516-5.svg", "url": "https://www.tripadvisor.com/ShowUserReviews-g190454-d230932-r680815321-Arthotel_ANA_Gala_Vienna-Vienna.html?m=21516#review680815321", "trip_type": "Friends getaway", "travel_date": "2019-05", "text": "My first trip to Vienna and we were supposed to stay somewhere in the city center, but our plans changed and we stayed here instead. The Hotel Adler is NOT in the city center. Don\u2019t let that bother...", "user": {"username": "Trevon P", "user_location": {"name": "Chicago", "id": null}}, "title": "A Good Hotel with Quick Links to Downtown Wien"}], "write_review": "https://www.tripadvisor.com/UserReview-g190454-d230932-m21516-Arthotel_ANA_Gala_Vienna-Vienna.html", "ancestors": [{"abbrv": null, "level": "City", "name": "Vienna", "location_id": "190454"}, {"abbrv": null, "level": "Region", "name": "Vienna Region", "location_id": "190453"}, {"abbrv": null, "level": "Country", "name": "Austria", "location_id": "190410"}], "longitude": "16.355167", "hours": null, "percent_recommended": 78, "review_rating_count": {"1": "8", "2": "2", "3": "20", "4": "57", "5": "46"}, "subratings": [{"rating_image_url": "https://static.tacdn.com/img2/ratings/traveler/ss4.0.gif", "name": "rate_location", "value": "4.0", "localized_name": "Location"}, {"rating_image_url": "https://static.tacdn.com/img2/ratings/traveler/ss4.0.gif", "name": "rate_sleep", "value": "4.0", "localized_name": "Sleep Quality"}, {"rating_image_url": "https://static.tacdn.com/img2/ratings/traveler/ss4.0.gif", "name": "rate_room", "value": "4.0", "localized_name": "Rooms"}, {"rating_image_url": "https://static.tacdn.com/img2/ratings/traveler/ss4.0.gif", "name": "rate_service", "value": "4.0", "localized_name": "Service"}, {"rating_image_url": "https://static.tacdn.com/img2/ratings/traveler/ss4.0.gif", "name": "rate_value", "value": "4.0", "localized_name": "Value"}, {"rating_image_url": "https://static.tacdn.com/img2/ratings/traveler/ss4.5.gif", "name": "rate_cleanliness", "value": "4.5", "localized_name": "Cleanliness"}], "ranking_data": {"ranking_string": "#22 of 129 B&Bs / Inns in Vienna", "ranking_out_of": "129", "geo_location_id": "190454", "ranking": "22", "geo_location_name": "Vienna", "ranking_string_detail": null}, "photo_count": "89", "location_string": "Vienna", "web_url": "https://www.tripadvisor.com/Hotel_Review-g190454-d230932-Reviews-Arthotel_ANA_Gala_Vienna-Vienna.html?m=21516", "price_level": "$$", "rating_image_url": "http://www.tripadvisor.com/img/cdsi/img2/ratings/traveler/4.0-21516-5.svg", "awards": [], "name": "Arthotel ANA Gala Vienna", "num_reviews": "133", "category": {"name": "hotel", "localized_name": "Hotel"}, "subcategory": [{"name": "bb", "localized_name": "Bed and Breakfast"}], "see_all_photos": "https://www.tripadvisor.com/Hotel_Review-g190454-d230932-m21516-Reviews-Arthotel_ANA_Gala_Vienna-Vienna.html#photos"}