{"address_obj": {"street1": "73 rue Boileau", "street2": "16th Arr", "city": "Paris", "state": null, "country": "France", "postalcode": "75016", "address_string": "73 rue Boileau 16th Arr, 75016 Paris France"}, "latitude": "48.841442", "rating": "2.5", "location_id": "231061", "trip_types": [{"name": "business", "value": "99", "localized_name": "Business"}, {"name": "couples", "value": "107", "localized_name": "Couples"}, {"name": "solo", "value": "43", "localized_name": "Solo travel"}, {"name": "family", "value": "42", "localized_name": "Family"}, {"name": "friends", "value": "39", "localized_name": "Friends getaway"}], "reviews": [{"id": "705058803", "lang": "en", "location_id": "231061", "published_date": "2019-08-31T12:49:42-0400", "rating": 3, "helpful_votes": "0", "rating_image_url": "http://www.tripadvisor.com/img/cdsi/img2/ratings/traveler/s3.0-21516-5.svg", "url": "https://www.tripadvisor.com/ShowUserReviews-g187147-d231061-r705058803-Hotel_Exelmans-Paris_Ile_de_France.html?m=21516#review705058803", "trip_type": null, "travel_date": "2019-07", "text": "The Hotel Exelmans is on the western side of the Sixteenth Arrondissement not far from the Seine. As the third stop of our European vacation from 25-27 July, our family liked the area of apartments...", "user": {"username": "RoadtripCowboy", "user_location": {"name": "Burlington, CT", "id": null}}, "title": "Good stay in the Sixteenth"}, {"id": "681056902", "lang": "en", "location_id": "231061", "published_date": "2019-06-12T11:58:11-0400", "rating": 1, "helpful_votes": "1", "rating_image_url": "http://www.tripadvisor.com/img/cdsi/img2/ratings/traveler/s1.0-21516-5.svg", "url": "https://www.tripadvisor.com/ShowUserReviews-g187147-d231061-r681056902-Hotel_Exelmans-Paris_Ile_de_France.html?m=21516#review681056902", "trip_type": "Friends getaway", "travel_date": "2019-06", "text": "WARNING!! DO NOT STOP AT THIS HOTEL. \n\nNotified whilst on the aircraft travelling to Paris that the hotel had no hot water for the 4 days of our stay. This seems to have been a problem for 2 months...", "user": {"username": "Tastylad", "user_location": {"name": null, "id": null}}, "title": "STILL NO HOT WATER - DO NOT BOOK!!"}, {"id": "679874801", "lang": "en", "location_id": "231061", "published_date": "2019-06-07T23:44:37-0400", "rating": 3, "helpful_votes": "0", "rating_image_url": "http://www.tripadvisor.com/img/cdsi/img2/ratings/traveler/s3.0-21516-5.svg", "url": "https://www.tripadvisor.com/ShowUserReviews-g187147-d231061-r679874801-Hotel_Exelmans-Paris_Ile_de_France.html?m=21516#review679874801", "trip_type": "Couples", "travel_date": "2019-06", "text": "Nice hotel, comfortable bed, small rooms but had all we needed! The breakfast was fine. Staircase was difficult with bags but in general a sufficient stay! I miss the space one gets with an Airbnb...", "user": {"username": "carolynp24", "user_location": {"name": "Sydney, Australia", "id": "255060"}}, "title": "Nice and Central "}, {"id": "677265279", "lang": "en", "location_id": "231061", "published_date": "2019-05-28T22:15:28-0400", "rating": 2, "helpful_votes": "0", "rating_image_url": "http://www.tripadvisor.com/img/cdsi/img2/ratings/traveler/s2.0-21516-5.svg", "url": "https://www.tripadvisor.com/ShowUserReviews-g187147-d231061-r677265279-Hotel_Exelmans-Paris_Ile_de_France.html?m=21516#review677265279", "trip_type": "Couples", "travel_date": "2019-05", "text": "This review could have been soooo much better, except one of the essentials for any hotel was missing - hot water!\n\nI know it\u2019s 2 star, but it\u2019s not a camp site and the prices reflect this.\n\nWe...", "user": {"username": "SusanM879", "user_location": {"name": "Melbourne, Australia", "id": "255100"}}, "title": "NO HOT WATER!!"}, {"id": "674046344", "lang": "en", "location_id": "231061", "published_date": "2019-05-14T14:41:02-0400", "rating": 3, "helpful_votes": "0", "rating_image_url": "http://www.tripadvisor.com/img/cdsi/img2/ratings/traveler/s3.0-21516-5.svg", "url": "https://www.tripadvisor.com/ShowUserReviews-g187147-d231061-r674046344-Hotel_Exelmans-Paris_Ile_de_France.html?m=21516#review674046344", "trip_type": "Couples", "travel_date": "2019-05", "text": "We booked this hotel for 3 nights and the 2nd day for 6-7 hours there was no hot water at all, and the 3rd day there was no water only from 12 noon till about 8.30 pm. I understand problems happen...", "user": {"username": "UneViePrivee", "user_location": {"name": "London", "id": null}}, "title": "Badly Managed Beautiful Hotel..."}], "write_review": "https://www.tripadvisor.com/UserReview-g187147-d231061-m21516-Hotel_Exelmans-Paris_Ile_de_France.html", "ancestors": [{"abbrv": null, "level": "City", "name": "Paris", "location_id": "187147"}, {"abbrv": null, "level": "Region", "name": "Ile-de-France", "location_id": "187144"}, {"abbrv": null, "level": "Country", "name": "France", "location_id": "187070"}], "longitude": "2.262691", "hours": null, "percent_recommended": 20, "review_rating_count": {"1": "109", "2": "72", "3": "87", "4": "58", "5": "30"}, "subratings": [{"rating_image_url": "https://static.tacdn.com/img2/ratings/traveler/ss3.5.gif", "name": "rate_location", "value": "3.5", "localized_name": "Location"}, {"rating_image_url": "https://static.tacdn.com/img2/ratings/traveler/ss2.5.gif", "name": "rate_sleep", "value": "2.5", "localized_name": "Sleep Quality"}, {"rating_image_url": "https://static.tacdn.com/img2/ratings/traveler/ss2.0.gif", "name": "rate_room", "value": "2.0", "localized_name": "Rooms"}, {"rating_image_url": "https://static.tacdn.com/img2/ratings/traveler/ss3.0.gif", "name": "rate_service", "value": "3.0", "localized_name": "Service"}, {"rating_image_url": "https://static.tacdn.com/img2/ratings/traveler/ss2.5.gif", "name": "rate_value", "value": "2.5", "localized_name": "Value"}, {"rating_image_url": "https://static.tacdn.com/img2/ratings/traveler/ss2.5.gif", "name": "rate_cleanliness", "value": "2.5", "localized_name": "Cleanliness"}], "ranking_data": {"ranking_string": "#1,692 of 1,839 hotels in Paris", "ranking_out_of": "1839", "geo_location_id": "187147", "ranking": "1692", "geo_location_name": "Paris", "ranking_string_detail": null}, "photo_count": "178", "location_string": "Paris, Ile-de-France", "web_url": "https://www.tripadvisor.com/Hotel_Review-g187147-d231061-Reviews-Hotel_Exelmans-Paris_Ile_de_France.html?m=21516", "price_level": "$", "rating_image_url": "http://www.tripadvisor.com/img/cdsi/img2/ratings/traveler/2.5-21516-5.svg", "awards": [], "name": "Hotel Exelmans", "num_reviews": "356", "category": {"name": "hotel", "localized_name": "Hotel"}, "subcategory": [{"name": "hotel", "localized_name": "Hotel"}], "see_all_photos": "https://www.tripadvisor.com/Hotel_Review-g187147-d231061-m21516-Reviews-Hotel_Exelmans-Paris_Ile_de_France.html#photos"}