{"address_obj": {"street1": "13 rue Rene Boulanger", "street2": "", "city": "Paris", "state": null, "country": "France", "postalcode": "75010", "address_string": "13 rue Rene Boulanger, 75010 Paris France"}, "latitude": "48.868923", "rating": "4.0", "location_id": "315153", "trip_types": [{"name": "business", "value": "56", "localized_name": "Business"}, {"name": "couples", "value": "132", "localized_name": "Couples"}, {"name": "solo", "value": "22", "localized_name": "Solo travel"}, {"name": "family", "value": "43", "localized_name": "Family"}, {"name": "friends", "value": "30", "localized_name": "Friends getaway"}], "reviews": [{"id": "720098234", "lang": "en", "location_id": "315153", "published_date": "2019-10-21T02:23:52-0400", "rating": 4, "helpful_votes": "0", "rating_image_url": "http://www.tripadvisor.com/img/cdsi/img2/ratings/traveler/s4.0-21516-5.svg", "url": "https://www.tripadvisor.com/ShowUserReviews-g187147-d315153-r720098234-Moris_Hotel-Paris_Ile_de_France.html?m=21516#review720098234", "trip_type": null, "travel_date": "2019-10", "text": "Pleasant hotel within easy reach of the main attractions and Eurostar.  A good range of restaurants in the immediate vicinity and  only a couple of minutes from the metro made it an ideal base for...", "user": {"username": "Debthefoodie", "user_location": {"name": "Northampton, United Kingdom", "id": "186349"}}, "title": "Nice hotel in good location"}, {"id": "710634820", "lang": "en", "location_id": "315153", "published_date": "2019-09-17T10:50:28-0400", "rating": 5, "helpful_votes": "0", "rating_image_url": "http://www.tripadvisor.com/img/cdsi/img2/ratings/traveler/s5.0-21516-5.svg", "url": "https://www.tripadvisor.com/ShowUserReviews-g187147-d315153-r710634820-Moris_Hotel-Paris_Ile_de_France.html?m=21516#review710634820", "trip_type": null, "travel_date": "2019-08", "text": "I was traveling with my teenage son, and we were both very pleased with the selection.  It was hard to find something affordable and nice with 3 weeks notice in the summer, plus needing 2 twin beds...", "user": {"username": "Patricia C", "user_location": {"name": "Del Mar, California", "id": "32286"}}, "title": "Excellent service, great value for the money, nice and clean, near a metro"}, {"id": "710506161", "lang": "en", "location_id": "315153", "published_date": "2019-09-17T02:54:18-0400", "rating": 4, "helpful_votes": "0", "rating_image_url": "http://www.tripadvisor.com/img/cdsi/img2/ratings/traveler/s4.0-21516-5.svg", "url": "https://www.tripadvisor.com/ShowUserReviews-g187147-d315153-r710506161-Moris_Hotel-Paris_Ile_de_France.html?m=21516#review710506161", "trip_type": "Business", "travel_date": "2019-08", "text": "I stay in Paris regularly for business and I always choose the Moris if they have availability. It's a 3 star hotel and it isn't pretending to be anything else. The staff are friendly enough, the...", "user": {"username": "Stewart W", "user_location": {"name": "Southend-on-Sea, United Kingdom", "id": "503790"}}, "title": "What you see is what you get"}, {"id": "709299934", "lang": "en", "location_id": "315153", "published_date": "2019-09-12T23:57:33-0400", "rating": 5, "helpful_votes": "0", "rating_image_url": "http://www.tripadvisor.com/img/cdsi/img2/ratings/traveler/s5.0-21516-5.svg", "url": "https://www.tripadvisor.com/ShowUserReviews-g187147-d315153-r709299934-Moris_Hotel-Paris_Ile_de_France.html?m=21516#review709299934", "trip_type": null, "travel_date": "2019-08", "text": "Want to recommend it because of the price, cleanness, good air conditioning of the room in hot month of August and all people that work in there and always helped with us with important suggestions...", "user": {"username": "0005157", "user_location": {"name": "Oslo, Norway", "id": "190479"}}, "title": "Want to recommend this hotel."}, {"id": "700789938", "lang": "en", "location_id": "315153", "published_date": "2019-08-19T10:46:23-0400", "rating": 4, "helpful_votes": "0", "rating_image_url": "http://www.tripadvisor.com/img/cdsi/img2/ratings/traveler/s4.0-21516-5.svg", "url": "https://www.tripadvisor.com/ShowUserReviews-g187147-d315153-r700789938-Moris_Hotel-Paris_Ile_de_France.html?m=21516#review700789938", "trip_type": "Family", "travel_date": "2019-08", "text": "A nice, clean hotel in a great location. Only a 2 min walk from the metro. The rooms are lovely, neat and spacious. We enjoyed the breakfast and the lady who served the breakfast was always friendly...", "user": {"username": "687augustp", "user_location": {"name": "Sheffield, United Kingdom", "id": "186364"}}, "title": "Great stay"}], "write_review": "https://www.tripadvisor.com/UserReview-g187147-d315153-m21516-Moris_Hotel-Paris_Ile_de_France.html", "ancestors": [{"abbrv": null, "level": "City", "name": "Paris", "location_id": "187147"}, {"abbrv": null, "level": "Region", "name": "Ile-de-France", "location_id": "187144"}, {"abbrv": null, "level": "Country", "name": "France", "location_id": "187070"}], "longitude": "2.357565", "hours": null, "percent_recommended": 73, "review_rating_count": {"1": "6", "2": "14", "3": "60", "4": "141", "5": "87"}, "subratings": [{"rating_image_url": "https://static.tacdn.com/img2/ratings/traveler/ss4.0.gif", "name": "rate_location", "value": "4.0", "localized_name": "Location"}, {"rating_image_url": "https://static.tacdn.com/img2/ratings/traveler/ss4.0.gif", "name": "rate_sleep", "value": "4.0", "localized_name": "Sleep Quality"}, {"rating_image_url": "https://static.tacdn.com/img2/ratings/traveler/ss4.0.gif", "name": "rate_room", "value": "4.0", "localized_name": "Rooms"}, {"rating_image_url": "https://static.tacdn.com/img2/ratings/traveler/ss4.0.gif", "name": "rate_service", "value": "4.0", "localized_name": "Service"}, {"rating_image_url": "https://static.tacdn.com/img2/ratings/traveler/ss4.0.gif", "name": "rate_value", "value": "4.0", "localized_name": "Value"}, {"rating_image_url": "https://static.tacdn.com/img2/ratings/traveler/ss4.5.gif", "name": "rate_cleanliness", "value": "4.5", "localized_name": "Cleanliness"}], "ranking_data": {"ranking_string": "#761 of 1,839 hotels in Paris", "ranking_out_of": "1839", "geo_location_id": "187147", "ranking": "761", "geo_location_name": "Paris", "ranking_string_detail": null}, "photo_count": "102", "location_string": "Paris, Ile-de-France", "web_url": "https://www.tripadvisor.com/Hotel_Review-g187147-d315153-Reviews-Moris_Hotel-Paris_Ile_de_France.html?m=21516", "price_level": "$$", "rating_image_url": "http://www.tripadvisor.com/img/cdsi/img2/ratings/traveler/4.0-21516-5.svg", "awards": [], "name": "Moris Hotel", "num_reviews": "308", "category": {"name": "hotel", "localized_name": "Hotel"}, "subcategory": [{"name": "hotel", "localized_name": "Hotel"}], "see_all_photos": "https://www.tripadvisor.com/Hotel_Review-g187147-d315153-m21516-Reviews-Moris_Hotel-Paris_Ile_de_France.html#photos"}